judo/__init__.py
judo/cli.py
judo/config.py
judo/gui.py
judo/registration.py
judo/app/__init__.py
judo/app/benchmark.py
judo/app/controller.py
judo/app/simulation.py
judo/app/structs.py
judo/app/utils.py
judo/app/visualization.py
judo/app/asset/viser-logo-light.png
judo/configs/benchmark_default.yaml
judo/configs/judo_default.yaml
judo/controller/__init__.py
judo/controller/controller.py
judo/controller/overrides.py
judo/examples/example_optimizer.py
judo/examples/example_task.py
judo/models/xml/README.md
judo/models/xml/caltech_leap_cube.xml
judo/models/xml/caltech_leap_cube_sim.xml
judo/models/xml/cartpole.xml
judo/models/xml/cylinder_push.xml
judo/models/xml/fr3_pick.xml
judo/models/xml/leap_cube.xml
judo/models/xml/leap_cube_palm_down.xml
judo/models/xml/leap_cube_palm_down_sim.xml
judo/models/xml/leap_cube_sim.xml
judo/models/xml/caltech_leap_components/assets.xml
judo/models/xml/caltech_leap_components/leap_rh.xml
judo/models/xml/caltech_leap_components/params_and_default.xml
judo/models/xml/caltech_leap_components/params_and_default_sim.xml
judo/models/xml/fr3_components/assets.xml
judo/models/xml/fr3_components/fr3.xml
judo/models/xml/fr3_components/params_and_default.xml
judo/models/xml/leap_components/assets.xml
judo/models/xml/leap_components/cube_pips_coll.xml
judo/models/xml/leap_components/cube_pips_vis.xml
judo/models/xml/leap_components/leap_hand.xml
judo/models/xml/leap_components/params_and_default.xml
judo/models/xml/leap_components/params_and_default_sim.xml
judo/optimizers/__init__.py
judo/optimizers/base.py
judo/optimizers/cem.py
judo/optimizers/mppi.py
judo/optimizers/overrides.py
judo/optimizers/ps.py
judo/tasks/README.md
judo/tasks/__init__.py
judo/tasks/base.py
judo/tasks/caltech_leap_cube.py
judo/tasks/cartpole.py
judo/tasks/cost_functions.py
judo/tasks/cylinder_push.py
judo/tasks/fr3_pick.py
judo/tasks/leap_cube.py
judo/tasks/leap_cube_down.py
judo/utils/__init__.py
judo/utils/asdf.py
judo/utils/assets.py
judo/utils/fields.py
judo_rai-0.0.3.dist-info/METADATA
judo_rai-0.0.3.dist-info/WHEEL
judo_rai-0.0.3.dist-info/entry_points.txt
judo_rai-0.0.3.dist-info/licenses/LICENSE
judo_rai-0.0.3.dist-info/RECORD
