Metadata-Version: 2.4
Name: judo-rai
Version: 0.0.3
Summary: Judo: a hackable sampling-based MPC toolbox
Project-URL: Documentation, https://bdaiinstitute.github.io/judo
Author: The Robotics and AI Institute, Preston Culbertson, Albert Li, Simon Le Cleac'h, Brandon Hung
License: MIT License
License-File: LICENSE
Classifier: Development Status :: 3 - Alpha
Classifier: License :: OSI Approved :: MIT License
Classifier: Operating System :: OS Independent
Classifier: Programming Language :: Python :: 3
Classifier: Programming Language :: Python :: 3.10
Classifier: Programming Language :: Python :: 3.11
Classifier: Programming Language :: Python :: 3.12
Classifier: Programming Language :: Python :: 3.13
Requires-Python: >=3.10
Requires-Dist: dora-utils
Requires-Dist: mujoco
Requires-Dist: numpy
Requires-Dist: pillow
Requires-Dist: requests
Requires-Dist: rich
Requires-Dist: scipy
Requires-Dist: viser>=1.0.0
Provides-Extra: dev
Requires-Dist: furo; extra == 'dev'
Requires-Dist: m2r2; extra == 'dev'
Requires-Dist: pre-commit; extra == 'dev'
Requires-Dist: pybind11-stubgen; extra == 'dev'
Requires-Dist: pyright; extra == 'dev'
Requires-Dist: pytest; extra == 'dev'
Requires-Dist: pytest-cov; extra == 'dev'
Requires-Dist: pytest-xdist; extra == 'dev'
Requires-Dist: ruff; extra == 'dev'
Requires-Dist: sphinx; extra == 'dev'
Requires-Dist: sphinx-autoapi; extra == 'dev'
Requires-Dist: sphinxcontrib-ansi-rai; extra == 'dev'
Requires-Dist: sphinxcontrib-programoutput-rai; extra == 'dev'
Provides-Extra: docs
Requires-Dist: furo; extra == 'docs'
Requires-Dist: m2r2; extra == 'docs'
Requires-Dist: sphinx; extra == 'docs'
Requires-Dist: sphinx-autoapi; extra == 'docs'
Requires-Dist: sphinxcontrib-ansi-rai; extra == 'docs'
Requires-Dist: sphinxcontrib-programoutput-rai; extra == 'docs'
